amigadev/__init__.py
amigadev/bumprev.py
amigadev/fdtool.py
amigadev/png2image.py
amigadev_utils-0.1.0.data/scripts/adu-bumprev
amigadev_utils-0.1.0.data/scripts/adu-dalf
amigadev_utils-0.1.0.data/scripts/adu-fdtool
amigadev_utils-0.1.0.data/scripts/adu-png2image
amigadev_utils-0.1.0.dist-info/METADATA
amigadev_utils-0.1.0.dist-info/WHEEL
amigadev_utils-0.1.0.dist-info/top_level.txt
amigadev_utils-0.1.0.dist-info/RECORD
