Metadata-Version: 2.1
Name: amigadev-utils
Version: 0.1.0
Summary: amigadev-utils is a collection of utilities for Amiga system development
Home-page: https://github.com/weiju/amigadev-utils
Author: Wei-ju Wu
Author-email: weiju.wu@gmail.com
Maintainer: Wei-ju Wu
Maintainer-email: weiju.wu@gmail.com
License: GPL V3
Keywords: amiga,system,development,classic,ecs,aga
Classifier: Development Status :: 4 - Beta
Classifier: Environment :: Console
Classifier: Intended Audience :: Developers
Classifier: Natural Language :: English
Classifier: License :: OSI Approved :: GNU General Public License v3 (GPLv3)
Classifier: Operating System :: OS Independent
Classifier: Programming Language :: Python
Classifier: Programming Language :: Python :: 3
Classifier: Programming Language :: Python :: Implementation :: CPython
Classifier: Topic :: Software Development :: Libraries :: Python Modules
Requires-Dist: pillow
Requires-Dist: Jinja2
